{
  "id": "imgs/FE data binding.excalidraw 1",
  "title": "FE data binding.excalidraw 1",
  "description": "==⚠  Switch to EXCALIDRAW VIEW in the MORE OPTIONS menu of this document. ⚠==",
  "source": "@site/docs/imgs/FE data binding.excalidraw 1.md",
  "sourceDirName": "imgs",
  "slug": "/imgs/FE data binding.excalidraw 1",
  "permalink": "/wljs-docs/imgs/FE data binding.excalidraw 1",
  "draft": false,
  "unlisted": false,
  "tags": [
    {
      "label": "excalidraw",
      "permalink": "/wljs-docs/tags/excalidraw"
    }
  ],
  "version": "current",
  "lastUpdatedAt": 1708970154,
  "formattedLastUpdatedAt": "Feb 26, 2024",
  "frontMatter": {
    "excalidraw-plugin": "parsed",
    "tags": [
      "excalidraw"
    ]
  }
}